pasarguard/__init__.py
pasarguard/api.py
pasarguard/enums.py
pasarguard/models.py
pasarguard/utils.py
pasarguard-0.0.8.dist-info/METADATA
pasarguard-0.0.8.dist-info/WHEEL
pasarguard-0.0.8.dist-info/RECORD
