Metadata-Version: 2.4
Name: pasarguard
Version: 0.0.8
Summary: Add your description here
Requires-Python: <3.15,>=3.10
Requires-Dist: datetime>=5.5
Requires-Dist: httpx>=0.28.1
Requires-Dist: paramiko>=4.0.0
Requires-Dist: pydantic<2.13,>=2.4.1
Requires-Dist: sshtunnel>=0.4.0
